{
  "ui": {
    "tabs": [
      {
        "id": "skills",
        "displayName": "Skills",
        "icon": "⚔️"
      },
      {
        "id": "inventory", 
        "displayName": "Inventory",
        "icon": "🎒"
      },
      {
        "id": "character",
        "displayName": "Character", 
        "icon": "👤"
      },
      {
        "id": "achievements",
        "displayName": "Achievements",
        "icon": "🏆"
      }
    ],
    "cssClasses": {
      "skillItem": "skill-item",
      "skillHeader": "skill-header",
      "skillName": "skill-name",
      "skillLevel": "skill-level",
      "skillProgressContainer": "skill-progress-container",
      "skillProgressBar": "skill-progress-bar",
      "skillProgressFill": "skill-progress-fill",
      "skillXp": "skill-xp",
      "actionButton": "action-button",
      "newUnlock": "new-unlock",
      "narrationMessage": "narration-message",
      "tabButton": "tab-button",
      "tabPanel": "tab-panel",
      "active": "active",
      "toast": "toast",
      "toastContainer": "toast-container"
    },
    "elementIds": {
      "narrationContent": "narration-content",
      "skillsContent": "skills-content",
      "actionsContent": "actions-content",
      "skillsTab": "skills-tab",
      "inventoryTab": "inventory-tab", 
      "characterTab": "character-tab",
      "achievementsTab": "achievements-tab",
      "toastContainer": "toast-container"
    }
  },
  "constants": {
    "xpMultiplier": 100,
    "defaultLevel": 1,
    "defaultXp": 0,
    "progressMax": 100
  },
  "skills": {
    "woodcutting": {
      "name": "Woodcutting",
      "displayName": "Woodcutting",
      "description": "Cut down trees and gather wood",
      "actions": [
        {
          "name": "Chop Oak",
          "displayName": "Chop Oak",
          "description": "Chop oak logs",
          "levelRequired": 1,
          "xpReward": 10,
          "itemReward": "oak_logs",
          "itemCount": 1,
          "unlockMessage": "You can now chop oak trees!",
          "flavorText": "You swing your axe at the oak tree and collect some logs."
        },
        {
          "name": "Chop Willow",
          "displayName": "Chop Willow", 
          "description": "Chop willow logs",
          "levelRequired": 5,
          "xpReward": 15,
          "itemReward": "willow_logs",
          "itemCount": 1,
          "unlockMessage": "You can now chop willow trees!",
          "flavorText": "The willow tree's branches bend as you gather some logs."
        },
        {
          "name": "Chop Maple",
          "displayName": "Chop Maple",
          "description": "Chop maple logs", 
          "levelRequired": 10,
          "xpReward": 25,
          "itemReward": "maple_logs",
          "itemCount": 1,
          "unlockMessage": "You can now chop maple trees!",
          "flavorText": "The maple tree's sturdy trunk yields some quality logs."
        },
        {
          "name": "Chop Yew",
          "displayName": "Chop Yew",
          "description": "Chop yew logs",
          "levelRequired": 20,
          "xpReward": 50,
          "itemReward": "yew_logs",
          "itemCount": 1,
          "unlockMessage": "You can now chop yew trees!",
          "flavorText": "The ancient yew tree slowly gives up some of its precious wood."
        },
        {
          "name": "Chop Magic",
          "displayName": "Chop Magic",
          "description": "Chop magic logs",
          "levelRequired": 30,
          "xpReward": 100,
          "itemReward": "magic_logs",
          "itemCount": 1,
          "unlockMessage": "You can now chop magic trees!",
          "flavorText": "The magic tree shimmers as your axe connects, releasing mystical logs."
        }
      ]
    },
    "fishing": {
      "name": "Fishing",
      "displayName": "Fishing", 
      "description": "Catch fish from various locations",
      "actions": [
        {
          "name": "Fish Shrimp",
          "displayName": "Fish Shrimp",
          "description": "Catch shrimp",
          "levelRequired": 1,
          "xpReward": 8,
          "itemReward": "shrimp",
          "itemCount": 1,
          "unlockMessage": "You can now fish for shrimp!",
          "flavorText": "You cast your net into the shallow water and catch some shrimp."
        },
        {
          "name": "Fish Sardine",
          "displayName": "Fish Sardine",
          "description": "Catch sardines",
          "levelRequired": 5,
          "xpReward": 12,
          "itemReward": "sardine",
          "itemCount": 1,
          "unlockMessage": "You can now fish for sardines!",
          "flavorText": "Your fishing rod bends slightly as you reel in a sardine."
        },
        {
          "name": "Fish Herring",
          "displayName": "Fish Herring",
          "description": "Catch herring",
          "levelRequired": 10,
          "xpReward": 20,
          "itemReward": "herring",
          "itemCount": 1,
          "unlockMessage": "You can now fish for herring!",
          "flavorText": "The water ripples as you pull a herring from the depths."
        },
        {
          "name": "Fish Salmon",
          "displayName": "Fish Salmon",
          "description": "Catch salmon",
          "levelRequired": 20,
          "xpReward": 40,
          "itemReward": "salmon",
          "itemCount": 1,
          "unlockMessage": "You can now fish for salmon!",
          "flavorText": "After a brief struggle, you catch a salmon from the rushing river."
        },
        {
          "name": "Fish Lobster",
          "displayName": "Fish Lobster",
          "description": "Catch lobster",
          "levelRequired": 40,
          "xpReward": 80,
          "itemReward": "lobster",
          "itemCount": 1,
          "unlockMessage": "You can now fish for lobster!",
          "flavorText": "Your lobster pot successfully traps a large lobster."
        },
        {
          "name": "Fish Shark",
          "displayName": "Fish Shark",
          "description": "Catch shark",
          "levelRequired": 76,
          "xpReward": 150,
          "itemReward": "shark",
          "itemCount": 1,
          "unlockMessage": "You can now fish for shark!",
          "flavorText": "With great effort, you manage to haul in a thrashing shark."
        }
      ]
    },
    "mining": {
      "name": "Mining",
      "displayName": "Mining",
      "description": "Mine various ores from the earth",
      "actions": [
        {
          "name": "Mine Copper",
          "displayName": "Mine Copper",
          "description": "Mine copper ore",
          "levelRequired": 1,
          "xpReward": 12,
          "itemReward": "copper_ore",
          "itemCount": 1,
          "unlockMessage": "You can now mine copper ore!",
          "flavorText": "You swing your pickaxe at the rock and extract some copper ore."
        },
        {
          "name": "Mine Tin",
          "displayName": "Mine Tin",
          "description": "Mine tin ore",
          "levelRequired": 1,
          "xpReward": 12,
          "itemReward": "tin_ore",
          "itemCount": 1,
          "unlockMessage": "You can now mine tin ore!",
          "flavorText": "You swing your pickaxe at the rock and obtain some tin."
        },
        {
          "name": "Mine Iron",
          "displayName": "Mine Iron",
          "description": "Mine iron ore",
          "levelRequired": 15,
          "xpReward": 25,
          "itemReward": "iron_ore",
          "itemCount": 1,
          "unlockMessage": "You can now mine iron ore!",
          "flavorText": "The rock crumbles under your pickaxe, revealing iron ore."
        },
        {
          "name": "Mine Coal",
          "displayName": "Mine Coal",
          "description": "Mine coal",
          "levelRequired": 30,
          "xpReward": 50,
          "itemReward": "coal",
          "itemCount": 1,
          "unlockMessage": "You can now mine coal!",
          "flavorText": "You chip away at the dark vein and collect some coal."
        },
        {
          "name": "Mine Gold",
          "displayName": "Mine Gold",
          "description": "Mine gold ore",
          "levelRequired": 40,
          "xpReward": 80,
          "itemReward": "gold_ore",
          "itemCount": 1,
          "unlockMessage": "You can now mine gold ore!",
          "flavorText": "A glint catches your eye as you mine a piece of gold ore."
        },
        {
          "name": "Mine Mithril",
          "displayName": "Mine Mithril",
          "description": "Mine mithril ore",
          "levelRequired": 55,
          "xpReward": 120,
          "itemReward": "mithril_ore",
          "itemCount": 1,
          "unlockMessage": "You can now mine mithril ore!",
          "flavorText": "The blue-tinted mithril ore breaks free after several strong strikes."
        },
        {
          "name": "Mine Adamantite",
          "displayName": "Mine Adamantite",
          "description": "Mine adamantite ore",
          "levelRequired": 70,
          "xpReward": 200,
          "itemReward": "adamantite_ore",
          "itemCount": 1,
          "unlockMessage": "You can now mine adamantite ore!",
          "flavorText": "With great effort, your pickaxe manages to dislodge some adamantite ore."
        },
        {
          "name": "Mine Runite",
          "displayName": "Mine Runite",
          "description": "Mine runite ore",
          "levelRequired": 85,
          "xpReward": 400,
          "itemReward": "runite_ore",
          "itemCount": 1,
          "unlockMessage": "You can now mine runite ore!",
          "flavorText": "The rare runite ore gleams as you extract it from the ancient rock."
        }
      ]
    }
  },
  "messages": {
    "welcome": "Hello world",
    "levelUp": "🎉 {skillName} level up! You are now level {level}.",
    "actionUnlocked": "🔓 New action unlocked: {actionName} (Level {level})",
    "actionCompleted": "{flavorText}",
    "unlockMessage": "{unlockMessage}",
    "configError": "Error: Could not load game configuration. Please refresh the page.",
    "configLoaded": "Game configuration loaded successfully",
    "skillsConfigLoaded": "Skills configuration loaded successfully",
    "skillsConfigError": "Error: Could not load skills configuration.",
    "gameSaved": "🔄 Game progress saved",
    "gameLoaded": "📥 Welcome back! Your progress has been loaded",
    "noSaveFound": "🆕 No saved game found. Starting a new game",
    "saveError": "⚠️ Failed to save game progress",
    "loadError": "⚠️ Failed to load saved game"
  },
  "gameSettings": {
    "xpFormula": "level * 100",
    "defaultLevel": 1,
    "defaultXp": 0,
    "initialWood": 0
  },
  "achievements": {
    "woodcutting_master": {
      "id": "woodcutting_master",
      "name": "Woodcutter's Mastery",
      "description": "Reach level 50 in Woodcutting",
      "category": "skills",
      "icon": "🪓",
      "points": 50,
      "secret": false,
      "requirements": {
        "skillLevel": {
          "woodcutting": 50
        }
      }
    },
    "fishing_master": {
      "id": "fishing_master", 
      "name": "Master Angler",
      "description": "Reach level 50 in Fishing",
      "category": "skills",
      "icon": "🎣",
      "points": 50,
      "secret": false,
      "requirements": {
        "skillLevel": {
          "fishing": 50
        }
      }
    },
    "mining_master": {
      "id": "mining_master",
      "name": "Master Miner", 
      "description": "Reach level 50 in Mining",
      "category": "skills",
      "icon": "⛏️",
      "points": 50,
      "secret": false,
      "requirements": {
        "skillLevel": {
          "mining": 50
        }
      }
    },
    "first_skill": {
      "id": "first_skill",
      "name": "Getting Started",
      "description": "Reach level 10 in any skill",
      "category": "progression",
      "icon": "⭐",
      "points": 10,
      "secret": false,
      "requirements": {
        "anySkillLevel": 10
      }
    },
    "skill_diversity": {
      "id": "skill_diversity",
      "name": "Jack of All Trades",
      "description": "Reach level 20 in three different skills",
      "category": "progression", 
      "icon": "🎭",
      "points": 25,
      "secret": false,
      "requirements": {
        "multipleSkillLevels": {
          "count": 3,
          "level": 20
        }
      }
    },
    "inventory_collector": {
      "id": "inventory_collector",
      "name": "Collector",
      "description": "Collect 10 different types of items",
      "category": "collection",
      "icon": "📦",
      "points": 15,
      "secret": false,
      "requirements": {
        "uniqueItems": 10
      }
    },
    "secret_discovery": {
      "id": "secret_discovery",
      "name": "Hidden Secrets",
      "description": "Discover a secret achievement",
      "category": "secrets",
      "icon": "🔍",
      "points": 100,
      "secret": true,
      "requirements": {
        "custom": "secret_discovery"
      }
    },
    "pet_best_friends": {
      "id": "pet_best_friends",
      "name": "Best Friends Forever!",
      "description": "Equip and name your first pet",
      "category": "pet",
      "icon": "🐾",
      "points": 10,
      "secret": false,
      "requirements": { "custom": "equip_and_name_first_pet" }
    },
    "pet_friendship_magic": {
      "id": "pet_friendship_magic",
      "name": "Friendship is Magic",
      "description": "Tame at least 6 unicorns, and have a baby dragon as a pet",
      "category": "pet",
      "icon": "🦄",
      "points": 25,
      "secret": false,
      "requirements": { "custom": "tame_6_unicorns_and_baby_dragon" }
    },
    "pet_zookeeper": {
      "id": "pet_zookeeper",
      "name": "Became a Zookeeper",
      "description": "Have 25 exotic animals in your possession",
      "category": "pet",
      "icon": "🦓",
      "points": 30,
      "secret": false,
      "requirements": { "custom": "have_25_exotic_animals" }
    },
    "loc_vera_nice": {
      "id": "loc_vera_nice",
      "name": "Vera Nice",
      "description": "Craft medicine in Alochester",
      "category": "location",
      "icon": "💊",
      "points": 10,
      "secret": false,
      "requirements": { "custom": "craft_medicine_alochester" }
    },
    "loc_vroom_varrum": {
      "id": "loc_vroom_varrum",
      "name": "Vroom Vroom in Varrum",
      "description": "Use a mechanized mount in the City of Varrum",
      "category": "location",
      "icon": "🏍️",
      "points": 10,
      "secret": false,
      "requirements": { "custom": "use_mech_mount_varrum" }
    },
    "loc_call_you_back": {
      "id": "loc_call_you_back",
      "name": "Marge, I'm going to have to call you back",
      "description": "Visit the city of Atlantis",
      "category": "location",
      "icon": "🌊",
      "points": 10,
      "secret": false,
      "requirements": { "custom": "visit_atlantis" }
    },
    "loc_dying_ways": {
      "id": "loc_dying_ways",
      "name": "The Dying Ways",
      "description": "Make a living sacrifice at Bonewater",
      "category": "location",
      "icon": "💀",
      "points": 20,
      "secret": false,
      "requirements": { "custom": "sacrifice_bonewater" }
    },
    "loc_purreeee": {
      "id": "loc_purreeee",
      "name": "Purrrreeee",
      "description": "Distill anything with Purified Water in the Town of Purewater",
      "category": "location",
      "icon": "💧",
      "points": 10,
      "secret": false,
      "requirements": { "custom": "distill_purewater" }
    },
    "loc_polite_eh": {
      "id": "loc_polite_eh",
      "name": "Everyone's Just So Polite, Eh?",
      "description": "Buy or sell syrup in Maple Run",
      "category": "location",
      "icon": "🍁",
      "points": 10,
      "secret": false,
      "requirements": { "custom": "trade_syrup_maple_run" }
    },
    "loc_mossmade": {
      "id": "loc_mossmade",
      "name": "Mossmade",
      "description": "Be from Mossy Stone and cook with moss in Mossy Glade",
      "category": "location",
      "icon": "🌿",
      "points": 10,
      "secret": false,
      "requirements": { "custom": "cook_moss_mossy_glade" }
    },
    "loc_no_eyes": {
      "id": "loc_no_eyes",
      "name": "No Eyes? No problem!",
      "description": "Explore the Void",
      "category": "location",
      "icon": "🕳️",
      "points": 20,
      "secret": false,
      "requirements": { "custom": "explore_void" }
    },
    "combat_bear_snack": {
      "id": "combat_bear_snack",
      "name": "Bear Snack",
      "description": "Be attacked by a bear",
      "category": "combat",
      "icon": "🐻",
      "points": 5,
      "secret": false,
      "requirements": { "custom": "attacked_by_bear" }
    },
    "combat_bears_kill": {
      "id": "combat_bears_kill",
      "name": "What doesn't kill you makes you stronger. Except Bears. Bears Kill you.",
      "description": "Dies from a bear attack in Beargulch",
      "category": "combat",
      "icon": "☠️",
      "points": 15,
      "secret": false,
      "requirements": { "custom": "die_bear_beargulch" }
    },
    "combat_so_fierce": {
      "id": "combat_so_fierce",
      "name": "So Fierce!",
      "description": "Destroy a training dummy",
      "category": "combat",
      "icon": "🥊",
      "points": 5,
      "secret": false,
      "requirements": { "custom": "destroy_training_dummy" }
    },
    "craft_smrt": {
      "id": "craft_smrt",
      "name": "SMRT",
      "description": "'Accidentally' eat your own poisoned food",
      "category": "crafting",
      "icon": "☠️",
      "points": 10,
      "secret": false,
      "requirements": { "custom": "eat_poisoned_food" }
    },
    "craft_fungi": {
      "id": "craft_fungi",
      "name": "He's such a Fungi",
      "description": "Learn Fun Guy's Fantastic Fungi Feast at Fun Guy's Friendly Tavern",
      "category": "crafting",
      "icon": "🍄",
      "points": 10,
      "secret": false,
      "requirements": { "custom": "learn_fungi_feast" }
    },
    "craft_fungi_familiar": {
      "id": "craft_fungi_familiar",
      "name": "From Fungi to Familiar",
      "description": "Use Animation spell on a mushroom, then use Animal Handling to capture as a pet",
      "category": "crafting",
      "icon": "🍄🐾",
      "points": 20,
      "secret": false,
      "requirements": { "custom": "animate_and_capture_mushroom" }
    },
    "craft_colors_wind": {
      "id": "craft_colors_wind",
      "name": "See the colors of the wind.",
      "description": "Eat a Rainbow Trout",
      "category": "crafting",
      "icon": "🌈🐟",
      "points": 5,
      "secret": false,
      "requirements": { "custom": "eat_rainbow_trout" }
    },
    "craft_trip": {
      "id": "craft_trip",
      "name": "Who wants to go on a trip?",
      "description": "Eat a Red Mushroom",
      "category": "crafting",
      "icon": "🍄",
      "points": 5,
      "secret": false,
      "requirements": { "custom": "eat_red_mushroom" }
    },
    "craft_burnt_toast": {
      "id": "craft_burnt_toast",
      "name": "BEEPBEEPBEEP SMOKEY TOAST!",
      "description": "Burn a loaf of bread.",
      "category": "crafting",
      "icon": "🍞🔥",
      "points": 5,
      "secret": false,
      "requirements": { "custom": "burn_bread" }
    },
    "craft_axellent": {
      "id": "craft_axellent",
      "name": "Axellent",
      "description": "Make and sharpen any axe from scratch",
      "category": "crafting",
      "icon": "🪓",
      "points": 10,
      "secret": false,
      "requirements": { "custom": "make_sharpen_axe" }
    },
    "craft_recipe_encyclopedia": {
      "id": "craft_recipe_encyclopedia",
      "name": "Encyclopedia of Recipes",
      "description": "Learn every recipe",
      "category": "crafting",
      "icon": "📚",
      "points": 50,
      "secret": false,
      "requirements": { "custom": "learn_all_recipes" }
    },
    "craft_adventurous_eater": {
      "id": "craft_adventurous_eater",
      "name": "Adventurous eater",
      "description": "Try 10 different species' specialty dishes",
      "category": "crafting",
      "icon": "🍽️",
      "points": 15,
      "secret": false,
      "requirements": { "custom": "try_10_species_dishes" }
    },
    "collect_glow": {
      "id": "collect_glow",
      "name": "Glow, Baby, Glow!",
      "description": "Collect 50 glowing flora and fauna",
      "category": "collection",
      "icon": "✨",
      "points": 20,
      "secret": false,
      "requirements": { "custom": "collect_50_glowing" }
    },
    "collect_fish": {
      "id": "collect_fish",
      "name": "Hook, Line, and Sinker",
      "description": "Catch every type of fish",
      "category": "collection",
      "icon": "🎣",
      "points": 30,
      "secret": false,
      "requirements": { "custom": "catch_all_fish" }
    },
    "collect_insect": {
      "id": "collect_insect",
      "name": "Just don't look at it...",
      "description": "Eat every type of insect",
      "category": "collection",
      "icon": "🐛",
      "points": 15,
      "secret": false,
      "requirements": { "custom": "eat_all_insects" }
    },
    "special_greatest_desire": {
      "id": "special_greatest_desire",
      "name": "The best thing to do is always to follow your greatest desire",
      "description": "Meet the Devil",
      "category": "special",
      "icon": "😈",
      "points": 50,
      "secret": true,
      "requirements": { "custom": "meet_devil" }
    },
    "special_one_way_trip": {
      "id": "special_one_way_trip",
      "name": "It's a one-way trip",
      "description": "Be on a boat in the River Styx",
      "category": "special",
      "icon": "⛴️",
      "points": 20,
      "secret": false,
      "requirements": { "custom": "boat_river_styx" }
    },
    "special_sucker": {
      "id": "special_sucker",
      "name": "You're such a sucker!",
      "description": "Capture a live octopus",
      "category": "special",
      "icon": "🐙",
      "points": 10,
      "secret": false,
      "requirements": { "custom": "capture_octopus" }
    },
    "special_what_now": {
      "id": "special_what_now",
      "name": "Well, what do we do now?",
      "description": "Beat the game",
      "category": "special",
      "icon": "🏆",
      "points": 100,
      "secret": false,
      "requirements": { "custom": "beat_game" }
    },
    "special_master_gifter": {
      "id": "special_master_gifter",
      "name": "Master Gifter",
      "description": "Bestow 25 favorite gifts to NPC characters",
      "category": "special",
      "icon": "🎁",
      "points": 20,
      "secret": false,
      "requirements": { "custom": "gift_25_npcs" }
    },
    "special_hell_froze": {
      "id": "special_hell_froze",
      "name": "Hell froze over...",
      "description": "Leave the Underworld via the River Styx",
      "category": "special",
      "icon": "❄️",
      "points": 30,
      "secret": false,
      "requirements": { "custom": "leave_underworld_styx" }
    },
    "special_giving": {
      "id": "special_giving",
      "name": "The gift that keeps on giving...",
      "description": "Survive a curse or being poisoned for a fortnight",
      "category": "special",
      "icon": "🧪",
      "points": 20,
      "secret": false,
      "requirements": { "custom": "survive_curse_fortnight" }
    },
    "special_overachiever": {
      "id": "special_overachiever",
      "name": "Overachiever",
      "description": "Completed all quests",
      "category": "special",
      "icon": "🌟",
      "points": 100,
      "secret": false,
      "requirements": { "custom": "complete_all_quests" }
    }
  }
} 